rpdk/core/__init__.py
rpdk/core/boto_helpers.py
rpdk/core/build_image.py
rpdk/core/cli.py
rpdk/core/data_loaders.py
rpdk/core/exceptions.py
rpdk/core/extensions.py
rpdk/core/filters.py
rpdk/core/generate.py
rpdk/core/init.py
rpdk/core/invoke.py
rpdk/core/package.py
rpdk/core/plugin_base.py
rpdk/core/plugin_registry.py
rpdk/core/project.py
rpdk/core/submit.py
rpdk/core/test.py
rpdk/core/type_name_resolver.py
rpdk/core/type_schema_loader.py
rpdk/core/upload.py
rpdk/core/validate.py
rpdk/core/contract/__init__.py
rpdk/core/contract/contract_plugin.py
rpdk/core/contract/hook_client.py
rpdk/core/contract/interface.py
rpdk/core/contract/resource_client.py
rpdk/core/contract/resource_generator.py
rpdk/core/contract/type_configuration.py
rpdk/core/contract/suite/__init__.py
rpdk/core/contract/suite/contract_asserts_commons.py
rpdk/core/contract/suite/hook/__init__.py
rpdk/core/contract/suite/hook/handler_pre_create.py
rpdk/core/contract/suite/hook/handler_pre_delete.py
rpdk/core/contract/suite/hook/handler_pre_update.py
rpdk/core/contract/suite/hook/hook_handler_commons.py
rpdk/core/contract/suite/resource/__init__.py
rpdk/core/contract/suite/resource/contract_asserts.py
rpdk/core/contract/suite/resource/handler_commons.py
rpdk/core/contract/suite/resource/handler_create.py
rpdk/core/contract/suite/resource/handler_delete.py
rpdk/core/contract/suite/resource/handler_misc.py
rpdk/core/contract/suite/resource/handler_update.py
rpdk/core/contract/suite/resource/handler_update_invalid.py
rpdk/core/data/logging.yaml
rpdk/core/data/managed-upload-infrastructure.yaml
rpdk/core/data/pytest-contract.ini
rpdk/core/data/examples/hook/sse.verification.v1.json
rpdk/core/data/examples/hook/targets/aws-s3-bucket.json
rpdk/core/data/examples/module/sample.json
rpdk/core/data/examples/resource/initech.tps.report.v1.json
rpdk/core/data/schema/base.definition.schema.v1.json
rpdk/core/data/schema/meta-schema.json
rpdk/core/data/schema/provider.configuration.definition.schema.hooks.v1.json
cloudformation_cli-0.2.39.dist-info/LICENSE
cloudformation_cli-0.2.39.dist-info/METADATA
cloudformation_cli-0.2.39.dist-info/WHEEL
cloudformation_cli-0.2.39.dist-info/entry_points.txt
cloudformation_cli-0.2.39.dist-info/top_level.txt
cloudformation_cli-0.2.39.dist-info/zip-safe
cloudformation_cli-0.2.39.dist-info/RECORD
