Metadata-Version: 2.1
Name: cloudformation-cli
Version: 0.2.39
Summary: UNKNOWN
Home-page: https://github.com/aws-cloudformation/aws-cloudformation-rpdk/
Author: Amazon Web Services
Author-email: aws-cloudformation-developers@amazon.com
License: Apache License 2.0
Keywords: Amazon Web Services AWS CloudFormation
Platform: UNKNOWN
Classifier: Development Status :: 5 - Production/Stable
Classifier: Environment :: Console
Classifier: Intended Audience :: Developers
Classifier: License :: OSI Approved :: Apache Software License
Classifier: Natural Language :: English
Classifier: Topic :: Software Development :: Build Tools
Classifier: Topic :: Software Development :: Code Generators
Classifier: Operating System :: OS Independent
Classifier: Programming Language :: Python :: 3 :: Only
Classifier: Programming Language :: Python :: 3.8
Classifier: Programming Language :: Python :: 3.9
Classifier: Programming Language :: Python :: 3.10
Classifier: Programming Language :: Python :: 3.11
Requires-Python: >=3.6
Requires-Dist: boto3>=1.10.20
Requires-Dist: Jinja2>=3.1.2
Requires-Dist: markupsafe>=2.1.0
Requires-Dist: jsonpatch
Requires-Dist: jsonschema<=4.17.3,>=3.0.0
Requires-Dist: pytest>=4.5.0
Requires-Dist: pytest-random-order>=1.0.4
Requires-Dist: pytest-localserver>=0.5.0
Requires-Dist: Werkzeug>=2.2.0
Requires-Dist: PyYAML>=6.0.1
Requires-Dist: requests>=2.22
Requires-Dist: hypothesis>=4.32
Requires-Dist: colorama>=0.4.1
Requires-Dist: docker>=4.3.1
Requires-Dist: ordered-set>=4.0.2
Requires-Dist: cfn-lint>=0.78.1
Requires-Dist: cfn-flip>=1.2.3
Requires-Dist: nested-lookup
Requires-Dist: botocore>=1.31.17
